{
  "writing": [
    {
      "title": "Training an Architectural Classifier (5 part series)",
      "link": "https://medium.com/@mcculloughrt/training-an-architectural-classifier-5f1b4f512368",
      "author": "on: Hackernoon"
    },
    {
      "title": "React/Redux with Mapbox",
      "link": "https://medium.com/@mcculloughrt/react-redux-with-mapbox-78fa3767211e",
      "author": "on: Hackernoon"
    },
    {
      "title": "Sketch Modeling with HoloLens",
      "link": "https://medium.com/@mcculloughrt/sketch-modeling-with-hololens-b12e8e411b85",
      "author": "on: Hackernoon"
    },
    {
      "title": "Neural Style Transfer of Satellite Imagery",
      "link": "https://medium.com/@mcculloughrt/neural-style-transfer-on-satellite-imagery-cbc6c207c949",
      "author": "on: Breathe Publication"
    }
  ],
  "books": [
    {
      "title": "The New Urban Crisis",
      "author": "Richard Florida",
      "link": "https://www.amazon.com/New-Urban-Crisis-Increasing-Segregation/dp/0465079741"
    },
    {
      "title": "Sapiens: A Brief History of Humankind",
      "author": "Yuval Noah Harari",
      "link": "https://www.amazon.com/Sapiens-Humankind-Yuval-Noah-Harari/dp/0062316095"
    },
    {
      "title": "Machine Learning Yearning (Draft Copy)",
      "author": "Andrew Ng",
      "link": "http://www.mlyearning.org/"
    }
  ],
  "articles": [
    {
      "title": "Democratizing Data at Airbnb",
      "author": "Medium",
      "link": "https://medium.com/airbnb-engineering/democratizing-data-at-airbnb-852d76c51770"
    },
    {
      "title": "BuzzFeed News Trained A Computer To Search For Hidden Spy Planes. This Is What We Found.",
      "author": "BuzzFeed News",
      "link": "https://www.buzzfeed.com/peteraldhous/hidden-spy-planes"
    },
    {
      "title": "What Recovery? The Case for Continued Expansionary Policy at the Fed",
      "author": "Roosevelt Institute",
      "link": "https://www.scribd.com/document/353402063/What-Recovery-The-Case-for-Continued-Expansionary-Policy-at-the-Fed#fullscreen&from_embed"
    },
    {
      "title": "How I built a wind map with WebGL",
      "author": "Vladimir Agafonkin",
      "link": "https://blog.mapbox.com/how-i-built-a-wind-map-with-webgl-b63022b5537f"
    }
  ]
}
